v_m_b/AOLogger.py
v_m_b/S3WorkFileManager.py
v_m_b/__init__.py
v_m_b/async_crawl.py
v_m_b/detectgraynb.py
v_m_b/getFolderFromLocators.py
v_m_b/init_app_logger.py
v_m_b/localManifestForWork.py
v_m_b/manifestBuilder.py
v_m_b/manifestCommons.py
v_m_b/manifestforwork.py
v_m_b/s3customtransfer.py
v_m_b/test_expandImageList.py
v_m_b/AOLog/AOLogger.py
v_m_b/AOLog/__init__.py
v_m_b/ImageRepository/FSImageRepository.py
v_m_b/ImageRepository/ImageGroupResolver.py
v_m_b/ImageRepository/ImageRepositoryBase.py
v_m_b/ImageRepository/ImageRepositoryFactory.py
v_m_b/ImageRepository/S3ImageRepository.py
v_m_b/ImageRepository/__init__.py
v_m_b/VolumeInfo/VolInfo.py
v_m_b/VolumeInfo/VolumeInfoBase.py
v_m_b/VolumeInfo/VolumeInfoBuda.py
v_m_b/VolumeInfo/VolumeInfoeXist.py
v_m_b/VolumeInfo/__init__.py
v_m_b/image/__init__.py
v_m_b/image/generateManifest.py
bdrc_volume_manifest_builder-1.3.1.dist-info/LICENSE
bdrc_volume_manifest_builder-1.3.1.dist-info/METADATA
bdrc_volume_manifest_builder-1.3.1.dist-info/WHEEL
bdrc_volume_manifest_builder-1.3.1.dist-info/entry_points.txt
bdrc_volume_manifest_builder-1.3.1.dist-info/top_level.txt
bdrc_volume_manifest_builder-1.3.1.dist-info/RECORD
