Metadata-Version: 2.1
Name: bdrc-volume-manifest-builder
Version: 1.3.1
Summary: Creates manifests for syncd works.
Home-page: https://github.com/buda-base/volume-manifest-builder/
Author: jimk
Author-email: jimk@tbrc.org
License: UNKNOWN
Platform: UNKNOWN
Classifier: Programming Language :: Python :: 3
Classifier: License :: OSI Approved :: MIT License
Classifier: Operating System :: OS Independent
Classifier: Development Status :: 5 - Production/Stable
Requires-Python: >=3.7
License-File: LICENSE
Requires-Dist: boto3
Requires-Dist: requests
Requires-Dist: lxml
Requires-Dist: pillow
Requires-Dist: botocore
Requires-Dist: boto
Requires-Dist: aiofiles
Requires-Dist: bdrc-util
